{
  "results": [
    {
      "id": "1000",
      "name": "Caltex Alexandra",
      "street": "360 Alexandra Rd., Singapore 159951",
      "city": "",
      "state": "",
      "country": "Singapore",
      "postalCode": "159951",
      "notes": "",
      "phoneNumber": "+65 6475 3380",
      "latitude": "1.29039",
      "longitude": "103.807",
      "operatingHours": "",
      "fuelId": "1000,1001,1002,1003",
      "amenitiesId": "1002,1003,1005,9045",
      "distance": 0,
      "filterIds": "fuelid_1000,fuelid_1001,fuelid_1002,fuelid_1003,amenityid_1002,amenityid_1003,amenityid_1005,amenityid_9045",
      "amenitiesName": [
        "Car Wash",
        "5-Star Refreshrooms",
        "Convenience Store",
        "AXS Station"
      ],
      "fuelsName": [
        "Platinum 98 with Techron",
        "Premium 95 with Techron",
        "Regular 92 with Techron",
        "Caltex Diesel with Techron D"
      ]
    },
    {
      "id": "1003",
      "name": "Caltex Balestier",
      "street": "542 Balestier Road, Singapore 329864",
      "city": "Singapore",
      "state": "",
      "country": "Singapore",
      "postalCode": "329864",
      "notes": "",
      "phoneNumber": "+65 6255 2873",
      "latitude": "1.32677",
      "longitude": "103.84507",
      "operatingHours": "",
      "fuelId": "1000,1001,1002,1003",
      "amenitiesId": "1002,1003,1005,9009,9036,9045",
      "distance": 0,
      "filterIds": "fuelid_1000,fuelid_1001,fuelid_1002,fuelid_1003,amenityid_1002,amenityid_1003,amenityid_1005,amenityid_9009,amenityid_9036,amenityid_9045",
      "amenitiesName": [
        "Car Wash",
        "5-Star Refreshrooms",
        "Convenience Store",
        "OCBC ATM",
        "Singpost POPStation",
        "AXS Station"
      ],
      "fuelsName": [
        "Platinum 98 with Techron",
        "Premium 95 with Techron",
        "Regular 92 with Techron",
        "Caltex Diesel with Techron D"
      ]
    },
    {
      "id": "1004",
      "name": "Caltex Beach Road",
      "street": "4870 Beach Road, Singapore 199586",
      "city": "Singapore",
      "state": "",
      "country": "Singapore",
      "postalCode": "199586",
      "notes": "",
      "phoneNumber": "+65 6392 5609",
      "latitude": "1.30373",
      "longitude": "103.86583",
      "operatingHours": "",
      "fuelId": "1000,1001,1002,1003",
      "amenitiesId": "1001,1002,1003,1005,9009,9036,9045",
      "distance": 0,
      "filterIds": "fuelid_1000,fuelid_1001,fuelid_1002,fuelid_1003,amenityid_1001,amenityid_1002,amenityid_1003,amenityid_1005,amenityid_9009,amenityid_9036,amenityid_9045",
      "amenitiesName": [
        "Tyre Bay",
        "Car Wash",
        "5-Star Refreshrooms",
        "Convenience Store",
        "OCBC ATM",
        "Singpost POPStation",
        "AXS Station"
      ],
      "fuelsName": [
        "Platinum 98 with Techron",
        "Premium 95 with Techron",
        "Regular 92 with Techron",
        "Caltex Diesel with Techron D"
      ]
    },
    {
      "id": "1005",
      "name": "Caltex Binjai Park",
      "street": "836 Dunearn Road, Singapore 589457",
      "city": "",
      "state": "",
      "country": "Singapore",
      "postalCode": "589457",
      "notes": "",
      "phoneNumber": "+65 6466 2407",
      "latitude": "1.33525",
      "longitude": "103.7868",
      "operatingHours": "",
      "fuelId": "1000,1001,1002,1003",
      "amenitiesId": "1003,1005,9045",
      "distance": 0,
      "filterIds": "fuelid_1000,fuelid_1001,fuelid_1002,fuelid_1003,amenityid_1003,amenityid_1005,amenityid_9045",
      "amenitiesName": [
        "5-Star Refreshrooms",
        "Convenience Store",
        "AXS Station"
      ],
      "fuelsName": [
        "Platinum 98 with Techron",
        "Premium 95 with Techron",
        "Regular 92 with Techron",
        "Caltex Diesel with Techron D"
      ]
    },
    {
      "id": "1007",
      "name": "Caltex Changi",
      "street": "78 Changi Road, Singapore 419714",
      "city": "",
      "state": "",
      "country": "Singapore",
      "postalCode": "419714",
      "notes": "",
      "phoneNumber": "+65 6344 6595",
      "latitude": "1.3163",
      "longitude": "103.90013",
      "operatingHours": "",
      "fuelId": "1000,1001,1002,1003",
      "amenitiesId": "1002,1003,1005,9037,9045",
      "distance": 0,
      "filterIds": "fuelid_1000,fuelid_1001,fuelid_1002,fuelid_1003,amenityid_1002,amenityid_1003,amenityid_1005,amenityid_9037,amenityid_9045",
      "amenitiesName": [
        "Car Wash",
        "5-Star Refreshrooms",
        "Convenience Store",
        "Budget Car Rental",
        "AXS Station"
      ],
      "fuelsName": [
        "Platinum 98 with Techron",
        "Premium 95 with Techron",
        "Regular 92 with Techron",
        "Caltex Diesel with Techron D"
      ]
    },
    {
      "id": "1008",
      "name": "Caltex Clementi",
      "street": "126 Clementi Avenue 2., Singapore 129930",
      "city": "",
      "state": "",
      "country": "Singapore",
      "postalCode": "129930",
      "notes": "",
      "phoneNumber": "+65 6776 7178",
      "latitude": "1.31471",
      "longitude": "103.769",
      "operatingHours": "",
      "fuelId": "1000,1001,1002,1003",
      "amenitiesId": "1002,1003,1005,1007,9045",
      "distance": 0,
      "filterIds": "fuelid_1000,fuelid_1001,fuelid_1002,fuelid_1003,amenityid_1002,amenityid_1003,amenityid_1005,amenityid_1007,amenityid_9045",
      "amenitiesName": [
        "Car Wash",
        "5-Star Refreshrooms",
        "Convenience Store",
        "Old Chang Kee",
        "AXS Station"
      ],
      "fuelsName": [
        "Platinum 98 with Techron",
        "Premium 95 with Techron",
        "Regular 92 with Techron",
        "Caltex Diesel with Techron D"
      ]
    },
    {
      "id": "1009",
      "name": "Caltex Dunearn",
      "street": "130 Dunearn Road, Singapore 309436",
      "city": "",
      "state": "",
      "country": "Singapore",
      "postalCode": "309436",
      "notes": "",
      "phoneNumber": "+65 6256 9525",
      "latitude": "1.31885",
      "longitude": "103.83335",
      "operatingHours": "",
      "fuelId": "1000,1001,1002,1003",
      "amenitiesId": "1000,1001,1002,1003,1005,1007,9009,9045",
      "distance": 0,
      "filterIds": "fuelid_1000,fuelid_1001,fuelid_1002,fuelid_1003,amenityid_1000,amenityid_1001,amenityid_1002,amenityid_1003,amenityid_1005,amenityid_1007,amenityid_9009,amenityid_9045",
      "amenitiesName": [
        "Workshop",
        "Tyre Bay",
        "Car Wash",
        "5-Star Refreshrooms",
        "Convenience Store",
        "Old Chang Kee",
        "OCBC ATM",
        "AXS Station"
      ],
      "fuelsName": [
        "Platinum 98 with Techron",
        "Premium 95 with Techron",
        "Regular 92 with Techron",
        "Caltex Diesel with Techron D"
      ]
    },
    {
      "id": "1010",
      "name": "Caltex East Coast",
      "street": "355 East Coast Road, Singapore 428972",
      "city": "",
      "state": "",
      "country": "Singapore",
      "postalCode": "428972",
      "notes": "",
      "phoneNumber": "+65 6342 2378",
      "latitude": "1.30907",
      "longitude": "103.9108",
      "operatingHours": "",
      "fuelId": "1000,1001,1002,1003",
      "amenitiesId": "1000,1001,1002,1003,1005,1007,9009,9045",
      "distance": 0,
      "filterIds": "fuelid_1000,fuelid_1001,fuelid_1002,fuelid_1003,amenityid_1000,amenityid_1001,amenityid_1002,amenityid_1003,amenityid_1005,amenityid_1007,amenityid_9009,amenityid_9045",
      "amenitiesName": [
        "Workshop",
        "Tyre Bay",
        "Car Wash",
        "5-Star Refreshrooms",
        "Convenience Store",
        "Old Chang Kee",
        "OCBC ATM",
        "AXS Station"
      ],
      "fuelsName": [
        "Platinum 98 with Techron",
        "Premium 95 with Techron",
        "Regular 92 with Techron",
        "Caltex Diesel with Techron D"
      ]
    },
    {
      "id": "1011",
      "name": "Caltex Frankel Avenue",
      "street": "71 Frankel Avenue, Singapore 458200",
      "city": "",
      "state": "",
      "country": "Singapore",
      "postalCode": "458200",
      "notes": "",
      "phoneNumber": "+65 6245 0807",
      "latitude": "1.31548",
      "longitude": "103.91907",
      "operatingHours": "",
      "fuelId": "1000,1001,1002,1003",
      "amenitiesId": "1000,1001,1003,1005",
      "distance": 0,
      "filterIds": "fuelid_1000,fuelid_1001,fuelid_1002,fuelid_1003,amenityid_1000,amenityid_1001,amenityid_1003,amenityid_1005",
      "amenitiesName": [
        "Workshop",
        "Tyre Bay",
        "5-Star Refreshrooms",
        "Convenience Store"
      ],
      "fuelsName": [
        "Platinum 98 with Techron",
        "Premium 95 with Techron",
        "Regular 92 with Techron",
        "Caltex Diesel with Techron D"
      ]
    },
    {
      "id": "1012",
      "name": "Caltex Holland",
      "street": "297 Holland Road, Singapore 278629",
      "city": "",
      "state": "",
      "country": "Singapore",
      "postalCode": "278629",
      "notes": "",
      "phoneNumber": "+65 6465 2091",
      "latitude": "1.31774",
      "longitude": "103.78545",
      "operatingHours": "",
      "fuelId": "1000,1001,1002,1003",
      "amenitiesId": "1003,1005,9009,9036,9046",
      "distance": 0,
      "filterIds": "fuelid_1000,fuelid_1001,fuelid_1002,fuelid_1003,amenityid_1003,amenityid_1005,amenityid_9009,amenityid_9036,amenityid_9046",
      "amenitiesName": [
        "5-Star Refreshrooms",
        "Convenience Store",
        "OCBC ATM",
        "Singpost POPStation",
        "Hotbake Sandwich Vending Machine"
      ],
      "fuelsName": [
        "Platinum 98 with Techron",
        "Premium 95 with Techron",
        "Regular 92 with Techron",
        "Caltex Diesel with Techron D"
      ]
    },
    {
      "id": "1013",
      "name": "Caltex Jalan Ahmad Ibrahim",
      "street": "400 Jalan Ahmad Ibrahim, Singapore 629153",
      "city": "",
      "state": "",
      "country": "Singapore",
      "postalCode": "629153",
      "notes": "",
      "phoneNumber": "+65 6265 1200",
      "latitude": "1.32328",
      "longitude": "103.69191",
      "operatingHours": "",
      "fuelId": "1000,1001,1002,1003",
      "amenitiesId": "1000,1001,1003,1005,9045",
      "distance": 0,
      "filterIds": "fuelid_1000,fuelid_1001,fuelid_1002,fuelid_1003,amenityid_1000,amenityid_1001,amenityid_1003,amenityid_1005,amenityid_9045",
      "amenitiesName": [
        "Workshop",
        "Tyre Bay",
        "5-Star Refreshrooms",
        "Convenience Store",
        "AXS Station"
      ],
      "fuelsName": [
        "Platinum 98 with Techron",
        "Premium 95 with Techron",
        "Regular 92 with Techron",
        "Caltex Diesel with Techron D"
      ]
    },
    {
      "id": "1014",
      "name": "Caltex Jalan Bukit Merah",
      "street": "3781 Jalan Bukit Merah, Singapore 159463",
      "city": "",
      "state": "",
      "country": "Singapore",
      "postalCode": "159463",
      "notes": "",
      "phoneNumber": "+65 6276 1800",
      "latitude": "1.28447",
      "longitude": "103.81505",
      "operatingHours": "",
      "fuelId": "1000,1001,1002,1003",
      "amenitiesId": "1000,1001,1002,1003,1005,9009,9045",
      "distance": 0,
      "filterIds": "fuelid_1000,fuelid_1001,fuelid_1002,fuelid_1003,amenityid_1000,amenityid_1001,amenityid_1002,amenityid_1003,amenityid_1005,amenityid_9009,amenityid_9045",
      "amenitiesName": [
        "Workshop",
        "Tyre Bay",
        "Car Wash",
        "5-Star Refreshrooms",
        "Convenience Store",
        "OCBC ATM",
        "AXS Station"
      ],
      "fuelsName": [
        "Platinum 98 with Techron",
        "Premium 95 with Techron",
        "Regular 92 with Techron",
        "Caltex Diesel with Techron D"
      ]
    },
    {
      "id": "1015",
      "name": "Caltex Jalan Buroh",
      "street": "210 Jalan Buroh, Singapore 609831",
      "city": "",
      "state": "",
      "country": "Singapore",
      "postalCode": "609831",
      "notes": "",
      "phoneNumber": "+65 6515 4931",
      "latitude": "1.30466",
      "longitude": "103.742",
      "operatingHours": "Mon-Fri: 7:00AM to 7:00PM<br>Sat: 7:00AM to 3:00PM<br>Sun and Public Holidays: Closed",
      "fuelId": "1000,1001,1003",
      "amenitiesId": "",
      "distance": 0,
      "filterIds": "fuelid_1000,fuelid_1001,fuelid_1003",
      "amenitiesName": null,
      "fuelsName": [
        "Platinum 98 with Techron",
        "Premium 95 with Techron",
        "Caltex Diesel with Techron D"
      ]
    },
    {
      "id": "1016",
      "name": "Caltex Jurong West",
      "street": "21 Jurong West Street 93, Singapore 648964",
      "city": "",
      "state": "",
      "country": "Singapore",
      "postalCode": "648964",
      "notes": "",
      "phoneNumber": "+65 6793 0880",
      "latitude": "1.33874",
      "longitude": "103.69273",
      "operatingHours": "",
      "fuelId": "1000,1001,1002,1003",
      "amenitiesId": "1002,1003,1005,1007,9009,9045",
      "distance": 0,
      "filterIds": "fuelid_1000,fuelid_1001,fuelid_1002,fuelid_1003,amenityid_1002,amenityid_1003,amenityid_1005,amenityid_1007,amenityid_9009,amenityid_9045",
      "amenitiesName": [
        "Car Wash",
        "5-Star Refreshrooms",
        "Convenience Store",
        "Old Chang Kee",
        "OCBC ATM",
        "AXS Station"
      ],
      "fuelsName": [
        "Platinum 98 with Techron",
        "Premium 95 with Techron",
        "Regular 92 with Techron",
        "Caltex Diesel with Techron D"
      ]
    },
    {
      "id": "1017",
      "name": "Caltex Lor Chuan",
      "street": "277 Lor Chuan Road, Singapore 556771",
      "city": "",
      "state": "",
      "country": "Singapore",
      "postalCode": "556771",
      "notes": "",
      "phoneNumber": "+65 6285 7672",
      "latitude": "1.3578",
      "longitude": "103.86785",
      "operatingHours": "",
      "fuelId": "1000,1001,1002,1003",
      "amenitiesId": "1000,1002,1003,1005,1007,9009,9045",
      "distance": 0,
      "filterIds": "fuelid_1000,fuelid_1001,fuelid_1002,fuelid_1003,amenityid_1000,amenityid_1002,amenityid_1003,amenityid_1005,amenityid_1007,amenityid_9009,amenityid_9045",
      "amenitiesName": [
        "Workshop",
        "Car Wash",
        "5-Star Refreshrooms",
        "Convenience Store",
        "Old Chang Kee",
        "OCBC ATM",
        "AXS Station"
      ],
      "fuelsName": [
        "Platinum 98 with Techron",
        "Premium 95 with Techron",
        "Regular 92 with Techron",
        "Caltex Diesel with Techron D"
      ]
    },
    {
      "id": "1018",
      "name": "Caltex MacPherson 465 ",
      "street": "465 Macpherson Road, Singapore 368183",
      "city": "",
      "state": "",
      "country": "Singapore",
      "postalCode": "368183",
      "notes": "",
      "phoneNumber": "+65 6289 8161",
      "latitude": "1.33268",
      "longitude": "103.88363",
      "operatingHours": "",
      "fuelId": "1000,1001,1002,1003",
      "amenitiesId": "1000,1001,1002,1003,1005,9009",
      "distance": 0,
      "filterIds": "fuelid_1000,fuelid_1001,fuelid_1002,fuelid_1003,amenityid_1000,amenityid_1001,amenityid_1002,amenityid_1003,amenityid_1005,amenityid_9009",
      "amenitiesName": [
        "Workshop",
        "Tyre Bay",
        "Car Wash",
        "5-Star Refreshrooms",
        "Convenience Store",
        "OCBC ATM"
      ],
      "fuelsName": [
        "Platinum 98 with Techron",
        "Premium 95 with Techron",
        "Regular 92 with Techron",
        "Caltex Diesel with Techron D"
      ]
    },
    {
      "id": "1020",
      "name": "Caltex Paya Lebar",
      "street": "128 Paya Lebar Road, Singapore 409013",
      "city": "",
      "state": "",
      "country": "Singapore",
      "postalCode": "409013",
      "notes": "",
      "phoneNumber": "+65 6749 8969",
      "latitude": "1.3255",
      "longitude": "103.89083",
      "operatingHours": "",
      "fuelId": "1000,1001,1002,1003",
      "amenitiesId": "1005,9046",
      "distance": 0,
      "filterIds": "fuelid_1000,fuelid_1001,fuelid_1002,fuelid_1003,amenityid_1005,amenityid_9046",
      "amenitiesName": [
        "Convenience Store",
        "Hotbake Sandwich Vending Machine"
      ],
      "fuelsName": [
        "Platinum 98 with Techron",
        "Premium 95 with Techron",
        "Regular 92 with Techron",
        "Caltex Diesel with Techron D"
      ]
    },
    {
      "id": "1021",
      "name": "Caltex Serangoon Avenue",
      "street": "559 Upp Serangoon Road, Singapore 534561",
      "city": "",
      "state": "",
      "country": "Singapore",
      "postalCode": "534561",
      "notes": "",
      "phoneNumber": "+65 6487 6113",
      "latitude": "1.34741",
      "longitude": "103.87163",
      "operatingHours": "",
      "fuelId": "1000,1001,1002,1003",
      "amenitiesId": "1002,1003,1005,9009,9036,9045",
      "distance": 0,
      "filterIds": "fuelid_1000,fuelid_1001,fuelid_1002,fuelid_1003,amenityid_1002,amenityid_1003,amenityid_1005,amenityid_9009,amenityid_9036,amenityid_9045",
      "amenitiesName": [
        "Car Wash",
        "5-Star Refreshrooms",
        "Convenience Store",
        "OCBC ATM",
        "Singpost POPStation",
        "AXS Station"
      ],
      "fuelsName": [
        "Platinum 98 with Techron",
        "Premium 95 with Techron",
        "Regular 92 with Techron",
        "Caltex Diesel with Techron D"
      ]
    },
    {
      "id": "1022",
      "name": "Caltex Tampines",
      "street": "1 Tampines Ave 8, Singapore 529594",
      "city": "",
      "state": "",
      "country": "Singapore",
      "postalCode": "529594",
      "notes": "",
      "phoneNumber": "+65 6260 1780",
      "latitude": "1.34941",
      "longitude": "103.92845",
      "operatingHours": "",
      "fuelId": "1000,1001,1002,1003",
      "amenitiesId": "1002,1003,1005,1007,9009,9045,9046",
      "distance": 0,
      "filterIds": "fuelid_1000,fuelid_1001,fuelid_1002,fuelid_1003,amenityid_1002,amenityid_1003,amenityid_1005,amenityid_1007,amenityid_9009,amenityid_9045,amenityid_9046",
      "amenitiesName": [
        "Car Wash",
        "5-Star Refreshrooms",
        "Convenience Store",
        "Old Chang Kee",
        "OCBC ATM",
        "AXS Station",
        "Hotbake Sandwich Vending Machine"
      ],
      "fuelsName": [
        "Platinum 98 with Techron",
        "Premium 95 with Techron",
        "Regular 92 with Techron",
        "Caltex Diesel with Techron D"
      ]
    },
    {
      "id": "1023",
      "name": "Caltex Tanjong Katong",
      "street": "265 Tanjong Katong Road, Singapore 437052",
      "city": "",
      "state": "",
      "country": "Singapore",
      "postalCode": "437052",
      "notes": "",
      "phoneNumber": "+65 6345 8260",
      "latitude": "1.30749",
      "longitude": "103.89565",
      "operatingHours": "",
      "fuelId": "1000,1001,1002,1003",
      "amenitiesId": "1003,1005,9009",
      "distance": 0,
      "filterIds": "fuelid_1000,fuelid_1001,fuelid_1002,fuelid_1003,amenityid_1003,amenityid_1005,amenityid_9009",
      "amenitiesName": [
        "5-Star Refreshrooms",
        "Convenience Store",
        "OCBC ATM"
      ],
      "fuelsName": [
        "Platinum 98 with Techron",
        "Premium 95 with Techron",
        "Regular 92 with Techron",
        "Caltex Diesel with Techron D"
      ]
    },
    {
      "id": "1024",
      "name": "Caltex Upper Serangoon",
      "street": "818 Upper Serangoon Road, Singapore 534677",
      "city": "",
      "state": "",
      "country": "Singapore",
      "postalCode": "534677",
      "notes": "",
      "phoneNumber": "+65 6288 2284",
      "latitude": "1.35569",
      "longitude": "103.88072",
      "operatingHours": "",
      "fuelId": "1000,1001,1002,1003",
      "amenitiesId": "1002,1003,1005,9009,9010,9045",
      "distance": 0,
      "filterIds": "fuelid_1000,fuelid_1001,fuelid_1002,fuelid_1003,amenityid_1002,amenityid_1003,amenityid_1005,amenityid_9009,amenityid_9010,amenityid_9045",
      "amenitiesName": [
        "Car Wash",
        "5-Star Refreshrooms",
        "Convenience Store",
        "OCBC ATM",
        "Car Polish Service",
        "AXS Station"
      ],
      "fuelsName": [
        "Platinum 98 with Techron",
        "Premium 95 with Techron",
        "Regular 92 with Techron",
        "Caltex Diesel with Techron D"
      ]
    },
    {
      "id": "1025",
      "name": "Caltex Upper Thomson",
      "street": "555 Upper Thomson Road, Singapore 574417",
      "city": "",
      "state": "",
      "country": "Singapore",
      "postalCode": "574417",
      "notes": "",
      "phoneNumber": "+65 6455 1786",
      "latitude": "1.37094",
      "longitude": "103.82823",
      "operatingHours": "",
      "fuelId": "1000,1001,1002,1003",
      "amenitiesId": "1000,1002,1003,1005,9045",
      "distance": 0,
      "filterIds": "fuelid_1000,fuelid_1001,fuelid_1002,fuelid_1003,amenityid_1000,amenityid_1002,amenityid_1003,amenityid_1005,amenityid_9045",
      "amenitiesName": [
        "Workshop",
        "Car Wash",
        "5-Star Refreshrooms",
        "Convenience Store",
        "AXS Station"
      ],
      "fuelsName": [
        "Platinum 98 with Techron",
        "Premium 95 with Techron",
        "Regular 92 with Techron",
        "Caltex Diesel with Techron D"
      ]
    },
    {
      "id": "1026",
      "name": "Caltex Whitley",
      "street": "236 Whitley Road, Singapore 297826",
      "city": "",
      "state": "",
      "country": "Singapore",
      "postalCode": "297826",
      "notes": "",
      "phoneNumber": "+65 6252 2568",
      "latitude": "1.32498",
      "longitude": "103.82693",
      "operatingHours": "",
      "fuelId": "1000,1001,1002,1003",
      "amenitiesId": "1001,1003,1005,9045",
      "distance": 0,
      "filterIds": "fuelid_1000,fuelid_1001,fuelid_1002,fuelid_1003,amenityid_1001,amenityid_1003,amenityid_1005,amenityid_9045",
      "amenitiesName": [
        "Tyre Bay",
        "5-Star Refreshrooms",
        "Convenience Store",
        "AXS Station"
      ],
      "fuelsName": [
        "Platinum 98 with Techron",
        "Premium 95 with Techron",
        "Regular 92 with Techron",
        "Caltex Diesel with Techron D"
      ]
    },
    {
      "id": "1028",
      "name": "Caltex Sembawang",
      "street": "62 Sembawang Road, Singapore 779089",
      "city": "",
      "state": "",
      "country": "Singapore",
      "postalCode": "779089",
      "notes": "",
      "phoneNumber": "+65 6452 1511",
      "latitude": "1.40349",
      "longitude": "103.81848",
      "operatingHours": "",
      "fuelId": "1000,1001,1002,1003",
      "amenitiesId": "1000,1001,1002,1003,1005,9035",
      "distance": 0,
      "filterIds": "fuelid_1000,fuelid_1001,fuelid_1002,fuelid_1003,amenityid_1000,amenityid_1001,amenityid_1002,amenityid_1003,amenityid_1005,amenityid_9035",
      "amenitiesName": [
        "Workshop",
        "Tyre Bay",
        "Car Wash",
        "5-Star Refreshrooms",
        "Convenience Store",
        ""
      ],
      "fuelsName": [
        "Platinum 98 with Techron",
        "Premium 95 with Techron",
        "Regular 92 with Techron",
        "Caltex Diesel with Techron D"
      ]
    },
    {
      "id": "10072",
      "name": "Caltex Chong Pang",
      "street": "3700 Yishun Ring Road, Singapore 768690",
      "city": "Singapore",
      "state": "",
      "country": "Singapore",
      "postalCode": "768690",
      "notes": "",
      "phoneNumber": "+6562571822",
      "latitude": "1.42984",
      "longitude": "103.82992",
      "operatingHours": "",
      "fuelId": "1000,1001,1002,1003",
      "amenitiesId": "1000,1003,1005,9009,9045,9046",
      "distance": 0,
      "filterIds": "fuelid_1000,fuelid_1001,fuelid_1002,fuelid_1003,amenityid_1000,amenityid_1003,amenityid_1005,amenityid_9009,amenityid_9045,amenityid_9046",
      "amenitiesName": [
        "Workshop",
        "5-Star Refreshrooms",
        "Convenience Store",
        "OCBC ATM",
        "AXS Station",
        "Hotbake Sandwich Vending Machine"
      ],
      "fuelsName": [
        "Platinum 98 with Techron",
        "Premium 95 with Techron",
        "Regular 92 with Techron",
        "Caltex Diesel with Techron D"
      ]
    }
  ]
}